binancetrader/__init__.py
binancetrader/binancetrader.py
binancetrader-0.0.5.dist-info/LICENCE
binancetrader-0.0.5.dist-info/METADATA
binancetrader-0.0.5.dist-info/WHEEL
binancetrader-0.0.5.dist-info/top_level.txt
binancetrader-0.0.5.dist-info/RECORD
