Metadata-Version: 2.1
Name: binancetrader
Version: 0.0.5
Summary: It is a client-side package of Jirnals trading system as a Binance REST Api-based SDK midleware. Valid Binance account and Jirnal account are required to work with this package.
Home-page: UNKNOWN
Author: Amir Ayat
Author-email: amirayat20@gmail.com
License: UNKNOWN
Platform: UNKNOWN
Classifier: Programming Language :: Python :: 3
Classifier: License :: OSI Approved :: MIT License
Classifier: Operating System :: OS Independent
Requires-Python: >=3.6
License-File: LICENCE
Requires-Dist: requests
